randos/__init__.py
randos/data/CITIES.txt
randos/data/COUNTRIES.txt
randos/data/EMOJIS.txt
randos/data/TOURIST_CITIES.txt
randos/data/TOURIST_DESTS.txt
tests/__init__.py
tests/test_randos.py
randos-0.0.20.dist-info/LICENSE
randos-0.0.20.dist-info/METADATA
randos-0.0.20.dist-info/WHEEL
randos-0.0.20.dist-info/top_level.txt
randos-0.0.20.dist-info/RECORD
