Metadata-Version: 2.1
Name: randos
Version: 0.0.20
Summary: A randomness library
Home-page: https://github.com/aljaroudi/randos-pip
Author: Mohammed Aljaroudi
Author-email: maljaroudi@sandiego.edu
License: UNKNOWN
Platform: UNKNOWN
Classifier: Programming Language :: Python :: 3.9
Classifier: Programming Language :: Python :: 3.8
Classifier: Programming Language :: Python :: 3.7
Classifier: License :: OSI Approved :: MIT License
Requires-Python: >=3.7
